MANIFEST.in
README.rst
setup.cfg
setup.py
aiclib/__init__.py
aiclib/common.py
aiclib/core.py
aiclib/helpers.py
aiclib/nvp.py
aiclib/nvpentity.py
aiclib/nvpquery.py
aiclib.egg-info/PKG-INFO
aiclib.egg-info/SOURCES.txt
aiclib.egg-info/dependency_links.txt
aiclib.egg-info/not-zip-safe
aiclib.egg-info/requires.txt
aiclib.egg-info/top_level.txt