Metadata-Version: 1.1
Name: aiclib
Version: 0.86
Summary: A declarative system to consume the NVP api.
Home-page: https://github.com/rackerlabs/aiclib
Author: Ozone Networking (Team Johnnie)
Author-email: justin.hammond@rackspace.com
License: Apache Software License
Keywords: aiclib nvp
Platform: UNKNOWN
Classifier: Development Status :: 4 - Beta
Classifier: License :: OSI Approved :: Apache Software License
Classifier: Operating System :: POSIX :: Linux
Classifier: Programming Language :: Python :: 2.7
Classifier: Programming Language :: Python :: 2.6
